econometricML/__init__.py
econometricML/_modidx.py
econometricML/ch1.py
econometricML/ch2.py
econometricML-0.0.2.dist-info/LICENSE
econometricML-0.0.2.dist-info/METADATA
econometricML-0.0.2.dist-info/WHEEL
econometricML-0.0.2.dist-info/entry_points.txt
econometricML-0.0.2.dist-info/top_level.txt
econometricML-0.0.2.dist-info/RECORD
