Metadata-Version: 2.1
Name: econometricML
Version: 0.0.2
Summary: Technical notes & documentation for Causal ML Textbook
Home-page: https://github.com/jakepenzak/econometricML
Author: Jacob Pieniazek
Author-email: jakepzak@gmail.com
License: Apache Software License 2.0
Keywords: nbdev jupyter notebook python
Classifier: Development Status :: 2 - Pre-Alpha
Classifier: Intended Audience :: Developers
Classifier: Natural Language :: English
Classifier: Programming Language :: Python :: 3.7
Classifier: Programming Language :: Python :: 3.8
Classifier: Programming Language :: Python :: 3.9
Classifier: Programming Language :: Python :: 3.10
Classifier: License :: OSI Approved :: Apache Software License
Requires-Python: >=3.7
License-File: LICENSE
Provides-Extra: dev
